mpi4py/MPI.h
mpi4py/MPI.mpich.cpython-38-x86_64-linux-gnu.so
mpi4py/MPI.openmpi.cpython-38-x86_64-linux-gnu.so
mpi4py/MPI.pxd
mpi4py/MPI.pyi
mpi4py/MPI_api.h
mpi4py/__init__.pxd
mpi4py/__init__.py
mpi4py/__init__.pyi
mpi4py/__main__.py
mpi4py/__main__.pyi
mpi4py/_mpiabi.py
mpi4py/_mpiabi.pyi
mpi4py/bench.py
mpi4py/bench.pyi
mpi4py/libmpi.pxd
mpi4py/py.typed
mpi4py/run.py
mpi4py/run.pyi
mpi4py/typing.py
mpi4py/typing.pyi
mpi4py/futures/__init__.py
mpi4py/futures/__init__.pyi
mpi4py/futures/__main__.py
mpi4py/futures/__main__.pyi
mpi4py/futures/_base.py
mpi4py/futures/_base.pyi
mpi4py/futures/_core.py
mpi4py/futures/_core.pyi
mpi4py/futures/aplus.py
mpi4py/futures/aplus.pyi
mpi4py/futures/pool.py
mpi4py/futures/pool.pyi
mpi4py/futures/server.py
mpi4py/futures/server.pyi
mpi4py/futures/util.py
mpi4py/futures/util.pyi
mpi4py/include/mpi4py/mpi.pxi
mpi4py/include/mpi4py/mpi4py.h
mpi4py/include/mpi4py/mpi4py.i
mpi4py/include/mpi4py/pycapi.h
mpi4py/util/__init__.py
mpi4py/util/__init__.pyi
mpi4py/util/dtlib.py
mpi4py/util/dtlib.pyi
mpi4py/util/pkl5.py
mpi4py/util/pkl5.pyi
mpi4py/util/pool.py
mpi4py/util/pool.pyi
mpi4py/util/sync.py
mpi4py/util/sync.pyi
mpi4py-4.1.1.dist-info/LICENSE.rst
mpi4py-4.1.1.dist-info/METADATA
mpi4py-4.1.1.dist-info/WHEEL
mpi4py-4.1.1.dist-info/top_level.txt
mpi4py-4.1.1.dist-info/RECORD
