Metadata-Version: 2.1
Name: mpi4py
Version: 4.1.1
Summary: Python bindings for MPI
Author: Lisandro Dalcin
Author-email: dalcinl@gmail.com
License: BSD-3-Clause
Project-URL: Homepage, https://mpi4py.github.io/mpi4py/
Project-URL: Documentation, https://mpi4py.readthedocs.io/en/stable/
Project-URL: Source, https://github.com/mpi4py/mpi4py
Project-URL: Issues, https://github.com/mpi4py/mpi4py/issues
Project-URL: Discussions, https://github.com/mpi4py/mpi4py/discussions
Project-URL: Downloads, https://github.com/mpi4py/mpi4py/releases
Keywords: scientific computing,parallel computing,message passing interface,MPI
Classifier: Development Status :: 6 - Mature
Classifier: Environment :: GPU
Classifier: Environment :: GPU :: NVIDIA CUDA
Classifier: Intended Audience :: Developers
Classifier: Intended Audience :: Science/Research
Classifier: Operating System :: MacOS
Classifier: Operating System :: MacOS :: MacOS X
Classifier: Operating System :: Microsoft :: Windows
Classifier: Operating System :: POSIX
Classifier: Operating System :: POSIX :: BSD
Classifier: Operating System :: POSIX :: Linux
Classifier: Operating System :: Unix
Classifier: Programming Language :: C
Classifier: Programming Language :: Cython
Classifier: Programming Language :: Python
Classifier: Programming Language :: Python :: 3
Classifier: Programming Language :: Python :: 3 :: Only
Classifier: Programming Language :: Python :: 3.8
Classifier: Programming Language :: Python :: 3.9
Classifier: Programming Language :: Python :: 3.10
Classifier: Programming Language :: Python :: 3.11
Classifier: Programming Language :: Python :: 3.12
Classifier: Programming Language :: Python :: 3.13
Classifier: Programming Language :: Python :: 3.14
Classifier: Programming Language :: Python :: Implementation :: CPython
Classifier: Programming Language :: Python :: Implementation :: PyPy
Classifier: Topic :: Scientific/Engineering
Classifier: Topic :: Software Development :: Libraries :: Python Modules
Classifier: Topic :: System :: Distributed Computing
Classifier: Typing :: Typed
Requires-Python: >=3.8
License-File: LICENSE.rst
